skyline.cp38-win32.pyd
skyline_solver/__init__.py
skyline_solver/skyline_solver.py
skyline_solver/skyline/__init__.py
skyline_solver-0.0.1.dist-info/LICENSE
skyline_solver-0.0.1.dist-info/METADATA
skyline_solver-0.0.1.dist-info/WHEEL
skyline_solver-0.0.1.dist-info/top_level.txt
skyline_solver-0.0.1.dist-info/RECORD
