Metadata-Version: 2.1
Name: skyline-solver
Version: 0.0.1
Summary: A Skyline solver for linear sets
Home-page: UNKNOWN
Author: Mojtaba Farrokh
License: UNKNOWN
Platform: UNKNOWN
Requires-Python: >=3
Requires-Dist: numpy
